[
  {
    "type": "bushfire",
    "title": "Bushfire Emergency Warning",
    "location": "Hills District, WA",
    "status": "Evacuate immediately",
    "description": "An uncontrolled bushfire is burning near residential areas.",
    "updated": "6 January 2026, 2:00 PM",
    "lat": -31.9535,
    "lng": 115.8570
  },
  {
    "type": "flood",
    "title": "Flood Watch",
    "location": "Swan River, WA",
    "status": "Monitor conditions",
    "description": "River levels rising due to heavy rainfall.",
    "updated": "6 January 2026, 12:30 PM",
    "lat": -31.9505,
    "lng": 115.8605
  }
]
